{
  "kind": "collectionType",
  "collectionName": "recipes",
  "info": {
    "name": "Recipe",
    "description": ""
  },
  "options": {
    "increments": true,
    "timestamps": true,
    "draftAndPublish": true
  },
  "attributes": {
    "name": {
      "type": "string"
    },
    "difficulty": {
      "type": "integer"
    },
    "link": {
      "type": "string"
    },
    "description": {
      "type": "text"
    },
    "image": {
      "collection": "file",
      "via": "related",
      "allowedTypes": [
        "images",
        "files",
        "videos"
      ],
      "plugin": "upload",
      "required": false
    }
  }
}
